pnt/__init__.py
pnt/pnt.py
pnt/AI_review_tools/AI_review_tools.py
pnt/AI_review_tools/__init__.py
pnt/AI_review_tools/base_filter_prompt.txt
pnt/AI_review_tools/base_summarize_prompt.txt
pnt/AI_review_tools/example_codebook.txt
pnt/AI_review_tools/overall_summary_prompt.txt
pnt-0.0.6.dist-info/licenses/LICENSE
pnt-0.0.6.dist-info/METADATA
pnt-0.0.6.dist-info/WHEEL
pnt-0.0.6.dist-info/top_level.txt
pnt-0.0.6.dist-info/RECORD
