Metadata-Version: 2.4
Name: pnt
Version: 0.0.6
Summary: A simple tool for generating and analyzing bibliometric citation network data from Pubmed.
Home-page: https://github.com/jarohde/pnt
Author: Jacob Rohde
Author-email: jarohde1@gmail.com
License: MIT
Classifier: Programming Language :: Python :: 3
Classifier: License :: OSI Approved :: MIT License
Classifier: Operating System :: OS Independent
Requires-Python: >=3.6
License-File: LICENSE
Requires-Dist: networkx
Requires-Dist: pandas
Requires-Dist: numpy
Requires-Dist: metapub
Requires-Dist: PyMuPDF
Dynamic: author
Dynamic: author-email
Dynamic: classifier
Dynamic: description
Dynamic: description-content-type
Dynamic: home-page
Dynamic: license
Dynamic: license-file
Dynamic: requires-dist
Dynamic: requires-python
Dynamic: summary
